examples/__init__.py
examples/airspacelib/__init__.py
examples/airspacelib/base/__init__.py
examples/airspacelib/base/aircraft.py
examples/airspacelib/base/aircraftarchitecture.py
examples/airspacelib/base/parameter.py
examples/airspacelib/base/state.py
examples/airspacelib/base/arch/__init__.py
examples/airspacelib/base/arch/aviate.py
examples/airspacelib/base/arch/controlflight.py
examples/airspacelib/base/arch/flows.py
examples/airspacelib/base/arch/holdpayload.py
examples/airspacelib/base/arch/perceiveenvironment.py
examples/airspacelib/base/arch/storeee.py
examples/airspacelib/contingencymanagement/__init__.py
examples/airspacelib/contingencymanagement/aircraft.py
examples/airspacelib/contingencymanagement/environment.py
examples/airspacelib/contingencymanagement/flightplanner.py
examples/airspacelib/wildfireresponse/__init__.py
examples/airspacelib/wildfireresponse/aircraft.py
examples/airspacelib/wildfireresponse/environment.py
examples/airspacelib/wildfireresponse/wildfiresim.py
examples/asg_demo/__init__.py
examples/asg_demo/demo_model.py
examples/eps/__init__.py
examples/eps/eps.py
examples/eps/test_eps.py
examples/multiflow_demo/__init__.py
examples/multiflow_demo/multiflow_demo.py
examples/multiflow_demo/test_multiflow.py
examples/multirotor/__init__.py
examples/multirotor/drone_mdl_dynamic.py
examples/multirotor/drone_mdl_hierarchical.py
examples/multirotor/drone_mdl_rural.py
examples/multirotor/drone_mdl_static.py
examples/multirotor/drone_mdl_urban.py
examples/multirotor/opt_drone_rural.py
examples/multirotor/test_multirotor.py
examples/pump/__init__.py
examples/pump/ex_pump.py
examples/pump/jointfaults_ex.py
examples/pump/parallelism_methods.py
examples/pump/pump_indiv.py
examples/pump/pump_stochastic.py
examples/pump/test_pump.py
examples/pump/test_pump_example.py
examples/pump/test_pump_stochastic.py
examples/rover/__init__.py
examples/rover/rover_degradation.py
examples/rover/rover_mode_space.py
examples/rover/rover_model.py
fmdtools-2.3.0.dist-info/licenses/LICENSE
fmdtools-2.3.0.dist-info/METADATA
fmdtools-2.3.0.dist-info/WHEEL
fmdtools-2.3.0.dist-info/top_level.txt
fmdtools-2.3.0.dist-info/RECORD
