Metadata-Version: 2.4
Name: fmdtools
Version: 2.3.0
Summary: System resilience modelling, simulation, and assessment in Python
Author: fmdtools Developers
Maintainer-email: Daniel Hulse <daniel.e.hulse@nasa.gov>
License: fmdtools version 2.3.0
Project-URL: Documentation, https://nasa.github.io/fmdtools/
Project-URL: source-code, https://github.com/nasa/fmdtools
Classifier: Development Status :: 5 - Production/Stable
Classifier: Intended Audience :: Science/Research
Classifier: Programming Language :: Python :: 3.11
Classifier: Programming Language :: Python :: 3.12
Classifier: Programming Language :: Python :: 3.13
Classifier: License :: OSI Approved :: Apache Software License
Classifier: Operating System :: OS Independent
Classifier: Topic :: Scientific/Engineering
Requires-Python: >=3.11
License-File: LICENSE
Requires-Dist: scipy
Requires-Dist: tqdm
Requires-Dist: networkx
Requires-Dist: numpy>=2.0
Requires-Dist: matplotlib>=3.7.0
Requires-Dist: pandas[all]
Requires-Dist: ordered-set
Requires-Dist: dill
Requires-Dist: recordclass==0.23.1
Requires-Dist: pytest
Requires-Dist: graphviz
Requires-Dist: shapely>=2.0
Dynamic: license-file
